rapid/__init__.py
rapid/robustness/__init__.py
rapid/robustness/analysis/__init__.py
rapid/robustness/analysis/comparisons.py
rapid/robustness/evaluator/__init__.py
rapid/robustness/evaluator/calc.py
rapid/robustness/metrics/__init__.py
rapid/robustness/metrics/common_metrics.py
rapid/robustness/metrics/custom_metrics.py
rapid/robustness/metrics/test/__init__.py
rapid/robustness/metrics/test/test_metrics.py
rapid/robustness/metrics/transforms/__init__.py
rapid/robustness/metrics/transforms/t1.py
rapid/robustness/metrics/transforms/t2.py
rapid/robustness/metrics/transforms/t3.py
rapid/robustness/metrics/transforms/test/__init__.py
rapid/robustness/metrics/transforms/test/test_t1.py
rapid/robustness/metrics/transforms/test/test_t2.py
rapid/robustness/metrics/transforms/test/test_t3.py
rapidrobustness-0.0.6.dist-info/LICENSE
rapidrobustness-0.0.6.dist-info/METADATA
rapidrobustness-0.0.6.dist-info/WHEEL
rapidrobustness-0.0.6.dist-info/top_level.txt
rapidrobustness-0.0.6.dist-info/RECORD
