Metadata-Version: 2.1
Name: rapidrobustness
Version: 0.0.6
Summary: Calculations and analyses of robustness.
Home-page: https://github.com/cameronmcphail/RAPID
Author: Cameron McPhail
Author-email: cameron.mcphail@adelaide.edu.au
License: UNKNOWN
Platform: UNKNOWN
Classifier: Programming Language :: Python :: 3
Classifier: License :: OSI Approved :: MIT License
Classifier: Operating System :: OS Independent
Requires-Dist: numpy
Requires-Dist: scipy
Requires-Dist: matplotlib
Requires-Dist: pandas
Requires-Dist: seaborn
Requires-Dist: ema-workbench
